{
    "error": false,
    "donate_url": "https://paypal.me/lucchetto",
    "website_url": "https://revengeos.com/",
    "news_url": "https://t.me/RevengeOSNews",
    "datetime": 1602325304.7329865,
    "filename": "RevengeOS-4.0-R-OFFICIAL-RMX1901-20201010-0800.zip",
    "id": "",
    "size": "949426142",
    "url": "https://osdn.net/frs/redir.php?f=%2Fstorage%2Fg%2Fr%2Fre%2Frevengeos%2FRMX1901%2FRevengeOS-4.0-R-OFFICIAL-RMX1901-20201010-0800.zip",
    "version": "4.0",
    "filehash": "a389593ea7ddb1e5f0c166f68c67b7bf"
}